{
	"__comment": "\nAdd durations, priority\nAdd actions without objects",
	"actions":{
		"faire_les_claps_1":{
			"type": "clap",
			"owner": "pr",
			"objectname": "clap__1",
			"startpoints": [{
				"x": 150,
				"y": 140,
				"a": 3.1416
			}],
			"sens": "osef",
			"priority": 18,
			"dependency": "prendre_gobelet_et_2_plots_front_left",
			"duration": 1,
			"orders":[{
				"name": "clap_1",
				"params": {}
				}],
			"kill": null
		},
		"faire_les_claps_3":{
			"type": "clap",
			"owner": "pr",
			"objectname": "clap__3",
			"startpoints": [{
				"x": 740,
				"y": 140,
				"a": 3.1416
			}],
			"sens": "osef",
			"priority": 17,
			"dependency": "",
			"duration": 1,
			"orders":[{
				"name": "clap_3",
				"params": {}
				}],
			"kill": null
		},
		"prendre_gobelet_et_2_plots_front_left":{
			"type": "gobelet",
			"owner": "pr",
			"objectname": "gobelet__front_left",
			"startpoints": [
			{
				"x": 450,
				"y": 350,
				"a": 0
			}],
			"sens": "arriere",
			"priority": 19,
			"dependency": "",
			"dependencyRobotContent": {
				"gobelet": false,
				"subPlot": 3,
				"invPlot": 0
				},
			"duration": 1,
			"orders":[{
				"name": "prendre_gobelet_et_2_plots_front",
				"params": {}
				}],
			"kill": null
		},
		"prendre_plot_middle_left1":{
			"type": "plot",
			"owner": "pr",
			"objectname": "plot__middle_left1",
			"startpoints": [],
			"sens": "avant",
			"priority": 20, 
			"dependency": "",
			"dependencyRobotContent": {
				"subPlot": 4,
				"invPlot": 0
				},
			"duration": 1,
			"orders":[{
				"name": "prendre_plot",
				"params": {}
				}],
			"kill": null
		},
		"prendre_plot_middle_left2":{
			"type": "plot",
			"owner": "pr",
			"objectname": "plot__middle_left2",
			"startpoints": [],
			"sens": "avant",
			"priority": 20, 
			"dependency": "",
			"dependencyRobotContent": {
				"subPlot": 4,
				"invPlot": 0
				},
			"duration": 1,
			"orders":[{
				"name": "prendre_plot",
				"params": {}
				}],
			"kill": null
		},
		"prendre_plot_middle_left3":{
			"type": "plot",
			"owner": "pr",
			"objectname": "plot__middle_left3",
			"startpoints": [],
			"sens": "avant",
			"priority": 20,  
			"dependency": "",
			"dependencyRobotContent": {
				"subPlot": 4,
				"invPlot": 0
				},
			"duration": 1,
			"orders":[{
				"name": "prendre_plot",
				"params": {}
				}],
			"kill": null
		},
		"deposer_pile_gobelet_prendre_balle_gauche":{
			"type": "depot_pile",
			"owner": "pr",
			"objectname": "pile__left",
			"startpoints": [{
				"x": 700,
				"y": 1000,
				"a": 3.1416
			}],
			"sens": "avant",
			"priority": 10,
			"dependency": "",
			"dependencyRobotContent": {
				"invPlot": 1
				},
			"duration": 1,
			"orders":[{
				"name": "deposer_pile_gobelet_prendre_balle_gauche",
				"params": {}
				}],
			"kill": null
		}
	}
}
